{
  "main": {
    "id": "e82473a935527c48",
    "type": "split",
    "children": [
      {
        "id": "aae3acb33071205e",
        "type": "tabs",
        "children": [
          {
            "id": "df7217a5f259da47",
            "type": "leaf",
            "state": {
              "type": "markdown",
              "state": {
                "file": "开发日志.md",
                "mode": "source",
                "source": false
              }
            }
          },
          {
            "id": "b2c294a00fad7664",
            "type": "leaf",
            "state": {
              "type": "markdown",
              "state": {
                "file": "1Documents/关于技术和思路/关于模块通信，数据解析.md",
                "mode": "source",
                "source": false
              }
            }
          },
          {
            "id": "3c0ea79d0e2daf4e",
            "type": "leaf",
            "state": {
              "type": "markdown",
              "state": {
                "file": "1Documents/关于技术和思路/关于UART的缓冲区.md",
                "mode": "source",
                "source": false
              }
            }
          }
        ],
        "currentTab": 2
      }
    ],
    "direction": "vertical"
  },
  "left": {
    "id": "d0a8197af77be04c",
    "type": "split",
    "children": [
      {
        "id": "5544783d72904997",
        "type": "tabs",
        "children": [
          {
            "id": "a1fc07e09f659c0d",
            "type": "leaf",
            "state": {
              "type": "file-explorer",
              "state": {
                "sortOrder": "alphabetical"
              }
            }
          },
          {
            "id": "13d84dcc3617b716",
            "type": "leaf",
            "state": {
              "type": "search",
              "state": {
                "query": "",
                "matchingCase": false,
                "explainSearch": false,
                "collapseAll": false,
                "extraContext": false,
                "sortOrder": "alphabetical"
              }
            }
          },
          {
            "id": "07c32d9ef4f5d396",
            "type": "leaf",
            "state": {
              "type": "starred",
              "state": {}
            }
          }
        ]
      }
    ],
    "direction": "horizontal",
    "width": 300
  },
  "right": {
    "id": "fe443e758247972a",
    "type": "split",
    "children": [
      {
        "id": "bd3bb369dd1509e6",
        "type": "tabs",
        "children": [
          {
            "id": "6857a7decb371a73",
            "type": "leaf",
            "state": {
              "type": "backlink",
              "state": {
                "file": "1Documents/关于技术和思路/关于UART的缓冲区.md",
                "collapseAll": false,
                "extraContext": false,
                "sortOrder": "alphabetical",
                "showSearch": false,
                "searchQuery": "",
                "backlinkCollapsed": false,
                "unlinkedCollapsed": true
              }
            }
          },
          {
            "id": "362d7947962eeee9",
            "type": "leaf",
            "state": {
              "type": "outgoing-link",
              "state": {
                "file": "1Documents/关于技术和思路/关于UART的缓冲区.md",
                "linksCollapsed": false,
                "unlinkedCollapsed": true
              }
            }
          },
          {
            "id": "4696d1a505bff457",
            "type": "leaf",
            "state": {
              "type": "tag",
              "state": {
                "sortOrder": "frequency",
                "useHierarchy": true
              }
            }
          },
          {
            "id": "b1a564350fbf5add",
            "type": "leaf",
            "state": {
              "type": "outline",
              "state": {
                "file": "1Documents/关于技术和思路/关于UART的缓冲区.md"
              }
            }
          }
        ]
      }
    ],
    "direction": "horizontal",
    "width": 300,
    "collapsed": true
  },
  "left-ribbon": {
    "hiddenItems": {
      "switcher:打开快速切换": false,
      "graph:查看关系图谱": false,
      "canvas:新建白板": false,
      "daily-notes:打开/创建今天的日记": false,
      "templates:插入模板": false,
      "command-palette:打开命令面板": false
    }
  },
  "active": "3c0ea79d0e2daf4e",
  "lastOpenFiles": [
    "2Drivers/RFID_Module.cpp",
    "2Drivers/RFID_Module.h",
    "2Drivers/RFID_Msg_Resolve.h",
    "2Drivers/RFID_Msg_Resolve.c",
    "1Documents/关于技术和思路/关于模块通信，数据解析.md",
    "1Documents/关于技术和思路/关于UART的缓冲区.md",
    "2Drivers/RFID_Reader.c",
    "2Drivers/RFID_Reader.h",
    "2Drivers",
    "新建文件夹",
    "开发日志.md",
    "9报名等资料/电子科学与工程学院D2222213基于RFID和激光雷达导航技术的分布式图书馆智慧终端意法.docx",
    "9报名等资料/意法半导体年度峰会视察小队补充资料.xlsx",
    "9报名等资料",
    "1Documents/KLM系列 模块资料（全）/android/UhfSDKdemo_1226_美标/UhfSDKdemo/bin/res/drawable-xxhdpi/ic_launcher.png",
    "1Documents/KLM系列 模块资料（全）/android/UhfSDKdemo_1226_美标/UhfSDKdemo/bin/res/drawable-xhdpi/ic_launcher.png",
    "1Documents/KLM系列 模块资料（全）/android/UhfSDKdemo_1226_美标/UhfSDKdemo/bin/res/drawable-mdpi/ic_launcher.png",
    "1Documents/KLM系列 模块资料（全）/android/UhfSDKdemo_1226_美标/UhfSDKdemo/bin/res/drawable-hdpi/plus.9.png",
    "1Documents/KLM系列 模块资料（全）/android/UhfSDKdemo_1226_美标/UhfSDKdemo/bin/res/drawable-hdpi/min.9.png",
    "1Documents/KLM系列 模块资料（全）/android/UhfSDKdemo_1226_美标/UhfSDKdemo/bin/res/drawable-hdpi/uhf_launcher.png",
    "1Documents/KLM系列 模块资料（全）/android/UhfSDKdemo_1226_美标/UhfSDKdemo/bin/res/drawable-hdpi/compose_icon_nextlevel.png",
    "1Documents/KLM系列 模块资料（全）/android/UhfSDKdemo_1226_美标/UhfSDKdemo/bin/res/drawable-hdpi/ic_launcher.png",
    "1Documents/KLM系列 模块资料（全）/android/UhfSDKdemo_1226_美标/UhfSDKdemo/res/drawable-xhdpi/ic_launcher.png",
    "1Documents/KLM系列 模块资料（全）/android/UhfSDKdemo_1226_美标/UhfSDKdemo/res/drawable-mdpi/ic_launcher.png"
  ]
}